{
  "Name": "alpinelinux3.21",
  "Upstream": "https://alpinelinux.org/cloud/",
  "Images": [
    {
      "Arch": "amd64",
      "Source": "https://dl-cdn.alpinelinux.org/alpine/v3.21/releases/cloud/",
      "Version": "3.21.4",
      "Account": "alpine",
      "FileUrl": "https://dl-cdn.alpinelinux.org/alpine/v3.21/releases/cloud/generic_alpine-3.21.4-x86_64-bios-cloudinit-r0.qcow2",
      "HashUrl": "https://dl-cdn.alpinelinux.org/alpine/v3.21/releases/cloud/generic_alpine-3.21.4-x86_64-bios-cloudinit-r0.qcow2.sha512",
      "HashFmt": "sha512sum:raw",
      "HashVal": "78609f1279eaea61fb4ebbefe173609dab9e0b1859a269e45171522576dedb66297448488d29ec417b34701c66e58835e0b74ca891279e075854290f259442bf"
    },
    {
      "Arch": "arm64",
      "Source": "https://dl-cdn.alpinelinux.org/alpine/v3.21/releases/cloud/",
      "Version": "3.21.2",
      "Account": "alpine",
      "FileUrl": "https://dl-cdn.alpinelinux.org/alpine/v3.21/releases/cloud/generic_alpine-3.21.2-aarch64-uefi-cloudinit-r0.qcow2",
      "HashUrl": "https://dl-cdn.alpinelinux.org/alpine/v3.21/releases/cloud/generic_alpine-3.21.2-aarch64-uefi-cloudinit-r0.qcow2.sha512",
      "HashFmt": "sha512sum:raw",
      "HashVal": "7f6439edaaf9fc208e4aede2c7e920adeb43ad0c8641164e3a9184809150357f426c99881c1157510833c5ab95f184e23dce2216ea9d591d3b479c3fe90ab9c8"
    }
  ]
}
